{
  "collapse-filter": true,
  "search": "",
  "showTags": true,
  "showAttachments": true,
  "hideUnresolved": true,
  "showOrphans": true,
  "collapse-color-groups": true,
  "colorGroups": [
    {
      "query": "path:Предметы/Информатика  ",
      "color": {
        "a": 1,
        "rgb": 5787135
      }
    },
    {
      "query": "path:\"Предметы/Математический анализ\"  ",
      "color": {
        "a": 1,
        "rgb": 16711680
      }
    },
    {
      "query": "path:\"Предметы/Алгебра и геометрия\"  ",
      "color": {
        "a": 1,
        "rgb": 65280
      }
    },
    {
      "query": "path:\"Предметы/Основы программирования\"  ",
      "color": {
        "a": 1,
        "rgb": 4369151
      }
    },
    {
      "query": "path:\"Предметы/Дискретная математика\"  ",
      "color": {
        "a": 1,
        "rgb": 5431443
      }
    }
  ],
  "collapse-display": true,
  "showArrow": true,
  "textFadeMultiplier": -3,
  "nodeSizeMultiplier": 1.08893229166667,
  "lineSizeMultiplier": 0.808203125,
  "collapse-forces": true,
  "centerStrength": 0.578125,
  "repelStrength": 20,
  "linkStrength": 1,
  "linkDistance": 223,
  "scale": 0.32133638605037484,
  "close": false
}